edc/__init__.py
edc/main.py
energy_dashboard_client-0.48.dist-info/LICENSE
energy_dashboard_client-0.48.dist-info/METADATA
energy_dashboard_client-0.48.dist-info/WHEEL
energy_dashboard_client-0.48.dist-info/entry_points.txt
energy_dashboard_client-0.48.dist-info/top_level.txt
energy_dashboard_client-0.48.dist-info/RECORD
