Metadata-Version: 2.1
Name: energy-dashboard-client
Version: 0.48
Summary: Energy Dashboard Command Line Interface (CLI)
Home-page: http://github.com/energy-analytics-project/energy-dashboard-cli
Author: Todd Greenwood-Geer (Enviro Software Solutions, LLC)
Author-email: pub+github@zwrob.com
License: UNKNOWN
Platform: UNKNOWN
Classifier: Development Status :: 3 - Alpha
Classifier: Intended Audience :: Developers
Classifier: Topic :: Software Development :: Build Tools
Classifier: License :: OSI Approved :: GNU General Public License v3 or later (GPLv3+)
Classifier: Programming Language :: Python :: 3.6
Requires-Dist: energy-dashboard-library (>=0.48)
Requires-Dist: Click
